_version.py
graphreadability/__init__.py
graphreadability/core/__init__.py
graphreadability/core/metricssuite.py
graphreadability/io/__init__.py
graphreadability/io/cytoscape_api.py
graphreadability/io/gefx_reader.py
graphreadability/io/graphml_reader.py
graphreadability/layout/__init__.py
graphreadability/layout/layout_algorithms.py
graphreadability/metrics/__init__.py
graphreadability/metrics/metric_helpers.py
graphreadability/metrics/metrics.py
graphreadability/tests/__init__.py
graphreadability/tests/test_helpers.py
graphreadability/tests/test_metric_helpers.py
graphreadability/tests/test_metrics.py
graphreadability/tests/test_metricssuite.py
graphreadability/tests/test_data/cube.graphml
graphreadability/tests/test_data/pretty_print_output.txt
graphreadability/tests/test_data/squares.graphml
graphreadability/tests/test_data/star.graphml
graphreadability/utils/__init__.py
graphreadability/utils/crosses_promotion.py
graphreadability/utils/helpers.py
graphreadability/utils/apps/digitize_graphs.py
graphreadability-0.0.3.dist-info/METADATA
graphreadability-0.0.3.dist-info/WHEEL
graphreadability-0.0.3.dist-info/licenses/LICENSE.txt
graphreadability-0.0.3.dist-info/RECORD
